{"ast":null,"code":"Inputmask(\"(99)99999-9999\").mask(document.getElementById(\"usuario_celular\"));\nInputmask(\"999.999.999-99\").mask(document.getElementById(\"usuario_cpf\"));","map":{"version":3,"sources":["/home/athos/Documentos/workspace/desafio-back-end/app/javascript/packs/usuarios.js"],"names":["Inputmask","mask","document","getElementById"],"mappings":"AAAAA,SAAS,CAAC,gBAAD,CAAT,CAA4BC,IAA5B,CAAiCC,QAAQ,CAACC,cAAT,CAAwB,iBAAxB,CAAjC;AACAH,SAAS,CAAC,gBAAD,CAAT,CAA4BC,IAA5B,CAAiCC,QAAQ,CAACC,cAAT,CAAwB,aAAxB,CAAjC","sourcesContent":["Inputmask(\"(99)99999-9999\").mask(document.getElementById(\"usuario_celular\"));\nInputmask(\"999.999.999-99\").mask(document.getElementById(\"usuario_cpf\")); "]},"metadata":{},"sourceType":"module"}